nonebot_plugin_user/__init__.py
nonebot_plugin_user/annotated.py
nonebot_plugin_user/config.py
nonebot_plugin_user/matchers.py
nonebot_plugin_user/models.py
nonebot_plugin_user/params.py
nonebot_plugin_user/py.typed
nonebot_plugin_user/utils.py
nonebot_plugin_user/migrations/9492159f98f7_remove_foreignkey.py
nonebot_plugin_user/migrations/__init__.py
nonebot_plugin_user/migrations/ac57f7074e58_init_db.py
nonebot_plugin_user/migrations/d6e05e49f79f_refactor_uninfo.py
nonebot_plugin_user/migrations/fc352174a592_add_email.py
nonebot_plugin_user-0.5.3.dist-info/METADATA
nonebot_plugin_user-0.5.3.dist-info/WHEEL
nonebot_plugin_user-0.5.3.dist-info/licenses/LICENSE
nonebot_plugin_user-0.5.3.dist-info/RECORD
