Metadata-Version: 2.4
Name: nonebot-plugin-user
Version: 0.5.3
Summary: 适用于 Nonebot2 的用户插件
Project-URL: Homepage, https://github.com/he0119/nonebot-plugin-user
Project-URL: Repository, https://github.com/he0119/nonebot-plugin-user.git
Project-URL: Issues, https://github.com/he0119/nonebot-plugin-user/issues
Project-URL: Changelog, https://github.com/he0119/nonebot-plugin-user/blob/main/CHANGELOG.md
Author-email: uy_sun <hmy0119@gmail.com>
License: MIT License
License-File: LICENSE
Requires-Python: >=3.9
Requires-Dist: expiringdictx>=1.1.0
Requires-Dist: nonebot-plugin-alconna>=0.37.1
Requires-Dist: nonebot-plugin-orm>=0.7.0
Requires-Dist: nonebot-plugin-uninfo>=0.7.3
Requires-Dist: nonebot2>=2.2.0
Provides-Extra: inspect
Requires-Dist: nonebot-plugin-inspect>=0.2.0; extra == 'inspect'
